wireshark_remote/__init__.py
wireshark_remote/cli.py
wireshark_remote/fritzbox_web.py
wireshark_remote-0.1.2.dist-info/METADATA
wireshark_remote-0.1.2.dist-info/WHEEL
wireshark_remote-0.1.2.dist-info/entry_points.txt
wireshark_remote-0.1.2.dist-info/licenses/LICENSE.txt
wireshark_remote-0.1.2.dist-info/RECORD
