Metadata-Version: 2.4
Name: wireshark_remote
Version: 0.1.2
Summary: Initiate wireshark remote capture (SSH or AVM FRITZ!Box)
Project-URL: Repository, https://github.com/fetzerch/wireshark_remote
Author-email: Christian Fetzer <fetzer.ch@gmail.com>
License-Expression: MIT
License-File: LICENSE.txt
Keywords: ssh,wireshark
Classifier: Development Status :: 4 - Beta
Classifier: Environment :: Console
Classifier: Intended Audience :: System Administrators
Classifier: Natural Language :: English
Classifier: Operating System :: POSIX
Classifier: Programming Language :: Python
Classifier: Topic :: System :: Systems Administration
Requires-Python: >=3.9
Requires-Dist: click>=8.1.8
